{
  "lock_version": 1,
  "barcode": "00000000018599",
  "indicator": "061.471 MAR 1974/75",
  "created_by": "admin",
  "last_modified_by": "admin",
  "create_time": "2016-08-13T09:25:44Z",
  "system_mtime": "2017-12-15T22:26:27Z",
  "user_mtime": "2016-08-13T09:25:44Z",
  "type": "volume",
  "jsonmodel_type": "top_container",
  "active_restrictions": [],
  "container_locations": [],
  "series": [],
  "collection": [
    {
      "ref": "/repositories/2/resources/1438",
      "identifier": "LI00309",
      "display_string": "Annual report"
    }
  ],
  "uri": "/repositories/2/top_containers/135617",
  "repository": {
    "ref": "/repositories/2"
  },
  "restricted": false,
  "is_linked_to_published_record": true,
  "display_string": "Volume 061.471 MAR 1974/75: [00000000018599]",
  "long_display_string": "LI00309, Volume 061.471 MAR 1974/75 [00000000018599]"
}