{
  "lock_version": 1,
  "barcode": "00000000021358",
  "indicator": "374.973 CEN 11",
  "created_by": "admin",
  "last_modified_by": "admin",
  "create_time": "2016-08-13T09:27:38Z",
  "system_mtime": "2017-12-15T22:26:27Z",
  "user_mtime": "2016-08-13T09:27:38Z",
  "type": "volume",
  "jsonmodel_type": "top_container",
  "active_restrictions": [],
  "container_locations": [],
  "series": [],
  "collection": [
    {
      "ref": "/repositories/2/resources/2478",
      "identifier": "LI01394",
      "display_string": "Occasional papers"
    }
  ],
  "uri": "/repositories/2/top_containers/137043",
  "repository": {
    "ref": "/repositories/2"
  },
  "restricted": false,
  "is_linked_to_published_record": true,
  "display_string": "Volume 374.973 CEN 11: [00000000021358]",
  "long_display_string": "LI01394, Volume 374.973 CEN 11 [00000000021358]"
}