{
  "lock_version": 1,
  "barcode": "00000000026384",
  "indicator": " 332.1092 ROC",
  "created_by": "sgandhi",
  "last_modified_by": "sgandhi",
  "create_time": "2018-03-01T21:40:05Z",
  "system_mtime": "2018-03-01T21:40:13Z",
  "user_mtime": "2018-03-01T21:40:05Z",
  "type": "item",
  "jsonmodel_type": "top_container",
  "active_restrictions": [],
  "container_locations": [],
  "series": [],
  "collection": [
    {
      "ref": "/repositories/2/resources/12508",
      "identifier": "LI19516",
      "display_string": "John Davison Rockefeller 1839-1937: A Memorial."
    }
  ],
  "uri": "/repositories/2/top_containers/177069",
  "repository": {
    "ref": "/repositories/2"
  },
  "restricted": false,
  "is_linked_to_published_record": true,
  "display_string": "Item  332.1092 ROC: [00000000026384]",
  "long_display_string": "LI19516, Item  332.1092 ROC [00000000026384]"
}