{
  "lock_version": 1,
  "barcode": "00000000026485",
  "indicator": "631.558 SAW",
  "created_by": "sgandhi",
  "last_modified_by": "sgandhi",
  "create_time": "2018-09-11T20:48:30Z",
  "system_mtime": "2018-09-11T20:49:50Z",
  "user_mtime": "2018-09-11T20:48:30Z",
  "type": "item",
  "jsonmodel_type": "top_container",
  "active_restrictions": [],
  "container_locations": [],
  "series": [],
  "collection": [
    {
      "ref": "/repositories/2/resources/12700",
      "identifier": "LI10619",
      "display_string": "Resilent crops for water limited environments: Proceedings of a workshop help at Cuernavaca, Mexico.  24-28 May, 2004."
    }
  ],
  "uri": "/repositories/2/top_containers/180779",
  "repository": {
    "ref": "/repositories/2"
  },
  "restricted": false,
  "is_linked_to_published_record": true,
  "display_string": "Item 631.558 SAW: [00000000026485]",
  "long_display_string": "LI10619, Item 631.558 SAW [00000000026485]"
}