{
  "lock_version": 1,
  "barcode": "00000000026488",
  "indicator": "631.558 HOU",
  "created_by": "sgandhi",
  "last_modified_by": "sgandhi",
  "create_time": "2018-09-14T19:20:13Z",
  "system_mtime": "2018-09-14T19:21:49Z",
  "user_mtime": "2018-09-14T19:20:13Z",
  "type": "item",
  "jsonmodel_type": "top_container",
  "active_restrictions": [],
  "container_locations": [],
  "series": [],
  "collection": [
    {
      "ref": "/repositories/2/resources/12705",
      "identifier": "LI10623",
      "display_string": "Biotechnology, breeding and seed systems for African crops.  Research and product development that reaches farmers."
    }
  ],
  "uri": "/repositories/2/top_containers/180857",
  "repository": {
    "ref": "/repositories/2"
  },
  "restricted": false,
  "is_linked_to_published_record": true,
  "display_string": "Item 631.558 HOU: [00000000026488]",
  "long_display_string": "LI10623, Item 631.558 HOU [00000000026488]"
}