{
  "lock_version": 2,
  "indicator": "001.3 KAU",
  "created_by": "admin",
  "last_modified_by": "admin",
  "create_time": "2016-08-13T09:26:32Z",
  "system_mtime": "2018-02-28T20:48:35Z",
  "user_mtime": "2016-08-13T09:26:32Z",
  "type": "volume",
  "jsonmodel_type": "top_container",
  "active_restrictions": [],
  "container_locations": [],
  "series": [],
  "collection": [
    {
      "ref": "/repositories/2/resources/1898",
      "identifier": "LI00771",
      "display_string": "The future of the humanities."
    }
  ],
  "uri": "/repositories/2/top_containers/136174",
  "repository": {
    "ref": "/repositories/2"
  },
  "restricted": false,
  "is_linked_to_published_record": true,
  "display_string": "Volume 001.3 KAU",
  "long_display_string": "LI00771, Volume 001.3 KAU"
}