{
  "lock_version": 2,
  "barcode": "00000000019206",
  "indicator": "959.803 FOR",
  "created_by": "admin",
  "last_modified_by": "admin",
  "create_time": "2016-08-13T09:26:49Z",
  "system_mtime": "2019-11-21T21:04:00Z",
  "user_mtime": "2016-08-13T09:26:49Z",
  "type": "volume",
  "jsonmodel_type": "top_container",
  "active_restrictions": [],
  "container_locations": [],
  "series": [],
  "collection": [
    {
      "ref": "/repositories/2/resources/2016",
      "identifier": "LI00889",
      "display_string": "Ford Foundation, Indonesia"
    }
  ],
  "uri": "/repositories/2/top_containers/136381",
  "repository": {
    "ref": "/repositories/2"
  },
  "restricted": false,
  "is_linked_to_published_record": true,
  "display_string": "Volume 959.803 FOR: [00000000019206]",
  "long_display_string": "LI00889, Volume 959.803 FOR [00000000019206]"
}