{
  "lock_version": 1,
  "indicator": "172 ETH",
  "created_by": "admin",
  "last_modified_by": "admin",
  "create_time": "2016-08-13T09:27:53Z",
  "system_mtime": "2017-12-15T22:26:27Z",
  "user_mtime": "2016-08-13T09:27:53Z",
  "type": "volume",
  "jsonmodel_type": "top_container",
  "active_restrictions": [],
  "container_locations": [],
  "series": [],
  "collection": [
    {
      "ref": "/repositories/2/resources/2646",
      "identifier": "LI01562",
      "display_string": "Ethics in hard times."
    }
  ],
  "uri": "/repositories/2/top_containers/137249",
  "repository": {
    "ref": "/repositories/2"
  },
  "restricted": false,
  "is_linked_to_published_record": true,
  "display_string": "Volume 172 ETH",
  "long_display_string": "LI01562, Volume 172 ETH"
}