{
  "lock_version": 1,
  "indicator": "303.6 KLI",
  "created_by": "admin",
  "last_modified_by": "admin",
  "create_time": "2016-08-13T09:28:19Z",
  "system_mtime": "2017-12-15T22:26:27Z",
  "user_mtime": "2016-08-13T09:28:19Z",
  "type": "volume",
  "jsonmodel_type": "top_container",
  "active_restrictions": [],
  "container_locations": [],
  "series": [],
  "collection": [
    {
      "ref": "/repositories/2/resources/2957",
      "identifier": "LI01873",
      "display_string": "Tensions affecting international understanding."
    }
  ],
  "uri": "/repositories/2/top_containers/137605",
  "repository": {
    "ref": "/repositories/2"
  },
  "restricted": false,
  "is_linked_to_published_record": true,
  "display_string": "Volume 303.6 KLI",
  "long_display_string": "LI01873, Volume 303.6 KLI"
}