{
  "lock_version": 1,
  "indicator": "324.6 GRO",
  "created_by": "admin",
  "last_modified_by": "admin",
  "create_time": "2016-08-13T09:29:12Z",
  "system_mtime": "2017-12-15T22:26:27Z",
  "user_mtime": "2016-08-13T09:29:12Z",
  "type": "volume",
  "jsonmodel_type": "top_container",
  "active_restrictions": [],
  "container_locations": [],
  "series": [],
  "collection": [
    {
      "ref": "/repositories/2/resources/3555",
      "identifier": "LI02471",
      "display_string": "Minority representation and the quest for voting equality."
    }
  ],
  "uri": "/repositories/2/top_containers/138294",
  "repository": {
    "ref": "/repositories/2"
  },
  "restricted": false,
  "is_linked_to_published_record": true,
  "display_string": "Volume 324.6 GRO",
  "long_display_string": "LI02471, Volume 324.6 GRO"
}