{
  "lock_version": 1,
  "indicator": "378.742 GRE",
  "created_by": "admin",
  "last_modified_by": "admin",
  "create_time": "2016-08-13T09:32:41Z",
  "system_mtime": "2017-12-15T22:26:27Z",
  "user_mtime": "2016-08-13T09:32:41Z",
  "type": "volume",
  "jsonmodel_type": "top_container",
  "active_restrictions": [],
  "container_locations": [],
  "series": [],
  "collection": [
    {
      "ref": "/repositories/2/resources/5898",
      "identifier": "LI04815",
      "display_string": "The undisciplinables: the senior fellowships at Dartmouth College, 1930-2000"
    }
  ],
  "uri": "/repositories/2/top_containers/141144",
  "repository": {
    "ref": "/repositories/2"
  },
  "restricted": false,
  "is_linked_to_published_record": true,
  "display_string": "Volume 378.742 GRE",
  "long_display_string": "LI04815, Volume 378.742 GRE"
}