{
  "lock_version": 1,
  "indicator": "616.2 MON",
  "created_by": "admin",
  "last_modified_by": "admin",
  "create_time": "2016-08-13T09:34:43Z",
  "system_mtime": "2017-12-15T22:26:27Z",
  "user_mtime": "2016-08-13T09:34:43Z",
  "type": "volume",
  "jsonmodel_type": "top_container",
  "active_restrictions": [],
  "container_locations": [],
  "series": [],
  "collection": [
    {
      "ref": "/repositories/2/resources/7279",
      "identifier": "LI06197",
      "display_string": "Obras."
    }
  ],
  "uri": "/repositories/2/top_containers/142748",
  "repository": {
    "ref": "/repositories/2"
  },
  "restricted": false,
  "is_linked_to_published_record": true,
  "display_string": "Volume 616.2 MON",
  "long_display_string": "LI06197, Volume 616.2 MON"
}