{
  "lock_version": 1,
  "indicator": "728.8 ASL",
  "created_by": "admin",
  "last_modified_by": "admin",
  "create_time": "2016-08-13T09:36:18Z",
  "system_mtime": "2017-12-15T22:26:27Z",
  "user_mtime": "2016-08-13T09:36:18Z",
  "type": "volume",
  "jsonmodel_type": "top_container",
  "active_restrictions": [],
  "container_locations": [],
  "series": [],
  "collection": [
    {
      "ref": "/repositories/2/resources/8301",
      "identifier": "LI07220",
      "display_string": "The country house as compromise: Kykuit."
    }
  ],
  "uri": "/repositories/2/top_containers/144031",
  "repository": {
    "ref": "/repositories/2"
  },
  "restricted": false,
  "is_linked_to_published_record": true,
  "display_string": "Volume 728.8 ASL",
  "long_display_string": "LI07220, Volume 728.8 ASL"
}