{
  "lock_version": 1,
  "barcode": "00000000039633",
  "indicator": "296.47 KLE ARMONK (FF BOX 6)",
  "created_by": "admin",
  "last_modified_by": "admin",
  "create_time": "2016-08-13T09:40:14Z",
  "system_mtime": "2017-12-15T22:26:27Z",
  "user_mtime": "2016-08-13T09:40:14Z",
  "type": "volume",
  "jsonmodel_type": "top_container",
  "active_restrictions": [],
  "container_locations": [],
  "series": [],
  "collection": [
    {
      "ref": "/repositories/2/resources/11003",
      "identifier": "LI09924",
      "display_string": "Listening for the oboe : a collection of drashot in honor of Rabbi Kleinbaum's tenth anniversary as spiritual leader of Congregation Beth Simchat Torah"
    }
  ],
  "uri": "/repositories/2/top_containers/147255",
  "repository": {
    "ref": "/repositories/2"
  },
  "restricted": false,
  "is_linked_to_published_record": true,
  "display_string": "Volume 296.47 KLE ARMONK (FF BOX 6): [00000000039633]",
  "long_display_string": "LI09924, Volume 296.47 KLE ARMONK (FF BOX 6) [00000000039633]"
}