{
  "lock_version": 1,
  "barcode": "00000000026273",
  "indicator": "309.223 373 HAN",
  "created_by": "sgandhi",
  "last_modified_by": "sgandhi",
  "create_time": "2017-05-31T21:17:27Z",
  "system_mtime": "2017-12-15T22:26:27Z",
  "user_mtime": "2017-05-31T21:17:27Z",
  "jsonmodel_type": "top_container",
  "active_restrictions": [],
  "container_locations": [],
  "series": [],
  "collection": [
    {
      "ref": "/repositories/2/resources/12151",
      "identifier": "LI10383",
      "display_string": "The U.S. and world development agenda for action 1976."
    }
  ],
  "uri": "/repositories/2/top_containers/169368",
  "repository": {
    "ref": "/repositories/2"
  },
  "restricted": false,
  "is_linked_to_published_record": true,
  "display_string": " 309.223 373 HAN: [00000000026273]",
  "long_display_string": "LI10383,  309.223 373 HAN [00000000026273]"
}