{
  "lock_version": 2,
  "barcode": "00000000023479",
  "indicator": "352.75 POP",
  "created_by": "sgandhi",
  "last_modified_by": "sgandhi",
  "create_time": "2017-11-17T21:36:35Z",
  "system_mtime": "2019-11-20T16:56:35Z",
  "user_mtime": "2017-11-17T21:36:35Z",
  "type": "item",
  "jsonmodel_type": "top_container",
  "active_restrictions": [],
  "container_locations": [],
  "series": [],
  "collection": [
    {
      "ref": "/repositories/2/resources/12373",
      "identifier": "LI10482",
      "display_string": "What the 1990 census tells us about women: A State Factbook."
    }
  ],
  "uri": "/repositories/2/top_containers/175183",
  "repository": {
    "ref": "/repositories/2"
  },
  "restricted": false,
  "is_linked_to_published_record": true,
  "display_string": "Item 352.75 POP: [00000000023479]",
  "long_display_string": "LI10482, Item 352.75 POP [00000000023479]"
}